<?xml version="1.0" ?><page xmlns="http://www.mediawiki.org/xml/export-0.8/" version="0.8">
    <title>Andrea Brown</title>
    <ns>0</ns>
    <id>2507008</id>
    <revision>
      <id>561771855</id>
      <parentid>497323527</parentid>
      <timestamp>2013-06-27T03:56:25Z</timestamp>
      <contributor>
        <username>ChrisGualtieri</username>
        <id>16333418</id>
      </contributor>
      <minor></minor>
      <comment>General Fixes + MOS + DMY changes using [[Project:AWB|AWB]]</comment>
      <text xml:space="preserve">{{Use dmy dates|date=June 2013}}
{{BLP sources|date=April 2010}}
{{Infobox musical artist
| name                = Andrea Brown
| image                 = 
| alt             = 
| caption            = 
| image_size            = 
| background          = solo_singer
| birth_name          = 
| alias               = 
| birth_date          = {{Birth date and age|df=yes|1974|2|17}}
| birth_place         = [[Boston, Massachusetts]]
| instrument          = [[Vocals]]
| occupation          = [[Singing|Singer]]
| years_active        = 2002
| label               = [[AM PM Records|AM:PM]], Groovilicious, Popular
}}
'''Andrea Brown''' (born 17 February 1974) is an [[African American]] female singer from [[Boston, Massachusetts]]. She is also the cousin of singer [[Bobby Brown]].

In 2002, she scored a #1 [[Hot Dance Music/Club Play]] track as the lead vocalist on [[Goldtrix]]'s cover of [[Jill Scott]]'s "It's Love (Trippin')".&lt;ref&gt;{{cite news|url=http://books.google.com/books?id=_w8EAAAAMBAJ&amp;pg=PA29&amp;dq=%22Andrea+Brown%22+%22It's+Love+(Trippin')%22&amp;hl=en&amp;ei=6hDFS8TbOsaqlAfT-eCCDA&amp;sa=X&amp;oi=book_result&amp;ct=result&amp;resnum=1&amp;ved=0CDYQ6AEwAA#v=onepage&amp;q=%22Andrea%20Brown%22%20%22It's%20Love%20(Trippin')%22&amp;f=false|title=The Beat Box Hot Plate|last=Paoletta|first=Michael|date=9 February 2002|work=[[Billboard (magazine)|Billboard]]|pages=29–30|accessdate=14 April 2010}}&lt;/ref&gt;

==References==
{{Reflist}}

==See also==
* [[List of number-one dance hits (United States)]]
* [[List of artists who reached number one on the US Dance chart]]

{{Persondata &lt;!-- Metadata: see [[Wikipedia:Persondata]]. --&gt;
| NAME              = Brown, Andrea
| ALTERNATIVE NAMES =
| SHORT DESCRIPTION =
| DATE OF BIRTH     = 17 February 1974
| PLACE OF BIRTH    = Boston, Massachusetts
| DATE OF DEATH     =
| PLACE OF DEATH    =
}}
{{DEFAULTSORT:Brown, Andrea}}
[[Category:African-American singers]]
[[Category:American dance musicians]]
[[Category:American female singers]]
[[Category:American rhythm and blues singers]]
[[Category:American house musicians]]
[[Category:People from Boston, Massachusetts]]
[[Category:Living people]]
[[Category:1974 births]]


{{US-RnB-singer-stub}}
{{house-musician-stub}}</text>
      <sha1>teggx4ya6c03dc975wz8y9cl4xjy0ex</sha1>
      <model>wikitext</model>
      <format>text/x-wiki</format>
    </revision>
  </page>