<?xml version="1.0" ?><page xmlns="http://www.mediawiki.org/xml/export-0.8/" version="0.8">
    <title>ECL, data-centric programming language for Big Data</title>
    <ns>0</ns>
    <id>36899245</id>
    <redirect title="ECL (data-centric programming language)"></redirect>
    <revision>
      <id>510427052</id>
      <timestamp>2012-09-02T13:36:55Z</timestamp>
      <contributor>
        <username>JHunterJ</username>
        <id>842922</id>
      </contributor>
      <comment>JHunterJ moved page [[ECL, data-centric programming language for Big Data]] to [[ECL (data-centric programming language)]]: naming conventions</comment>
      <text xml:space="preserve">#REDIRECT [[ECL (data-centric programming language)]]</text>
      <sha1>stv2k66m983cn7cj28hy5w7hn6c86nb</sha1>
      <model>wikitext</model>
      <format>text/x-wiki</format>
    </revision>
  </page>