<?xml version="1.0" ?><page xmlns="http://www.mediawiki.org/xml/export-0.8/" version="0.8">
    <title>Lučenec District</title>
    <ns>0</ns>
    <id>5018151</id>
    <revision>
      <id>541013663</id>
      <parentid>537708975</parentid>
      <timestamp>2013-02-27T18:55:55Z</timestamp>
      <contributor>
        <username>JAnDbot</username>
        <id>1725149</id>
      </contributor>
      <minor></minor>
      <comment>r2.7.2) (Robot: Removing be-x-old, cs, cv, de, eo, es, fr, hr, hu, it, la, nl, pl, pt, ru, rue, sk, uk, war</comment>
      <text xml:space="preserve">{{Infobox Slovak district |&lt;!--ARTICLE'S INFOBOX -- SCROLL DOWN SEVERAL LINES FOR ARTICLE'S SUMMARY--&gt;
 subject_name = Lučenec District |
 slovak_region = [[Banská Bystrica Region]] |
 population = 72837 |
 population_as_of = 2001 |
 prefix = 47 |
 area = 797 |
 car_plate = LC |
 image_location = Okres lucenec.png |
}}&lt;!--//END OF INFOBOX--&gt;

'''Lučenec District''' (''okres Lučenec'') is a [[district]] in the [[Banská Bystrica Region]] of south-central [[Slovakia]]. Until 1918, most of the district belong to the [[Nógrád (former county)|Novohrad]] county, with a small area around the villages of [[Šíd]], [[Čamovce]] and [[Šurice]] in the east belonging to the [[Gömör-Kishont|Gemer a Malohont]] county.

The district is situated in the [[Southern Slovak Basin]], in the broad valley of the [[Ipeľ River]].
The two towns&amp;mdash;[[Lučenec]] and [[Fiľakovo]]&amp;mdash;comprise nearly 54% of the population of the district, the remainder living in the 55 surrounding villages.

The district lies on the [[European route E571|E571]] route (Route 50 in Slovak numbering) from [[Bratislava]] to [[Košice]], and on one of the train lines connecting the two cities. Train services also run to [[Budapest]] via Fiľakovo. There is a small aerodrome at [[Boľkovce]].

The main industries are food processing and building materials.

== Municipalities==
*[[Ábelová]]
*[[Belina]]
*[[Biskupice, Lučenec District|Biskupice]]
*[[Boľkovce]]
*[[Budiná]]
*[[Bulhary, Lučenec District|Bulhary]]
*[[Buzitka]]
*[[Čakanovce, Lučenec District|Čakanovce]]
*[[Čamovce]]
*[[Divín]]
*[[Dobroč]]
*[[Fiľakovo]]
*[[Fiľakovské Kováče]]
*[[Gregorova Vieska]]
*[[Halič]]
*[[Holiša]]
*[[Jelšovec]]
*[[Kalonda]]
*[[Kotmanová]]
*[[Lehôtka]]
*[[Lentvora]]
*[[Lipovany]]
*[[Lovinobaňa]]
*[[Ľuboreč]]
*[[Lučenec]]
*[[Lupoč]]
*[[Mašková]]
*[[Mikušovce, Lučenec District|Mikušovce]]
*[[Mučín]]
*[[Mýtna]]
*[[Nitra nad Ipľom]]
*[[Nové Hony]]
*[[Panické Dravce]]
*[[Píla, Lučenec District|Píla]]
*[[Pinciná]]
*[[Pleš, Slovakia|Pleš]]
*[[Podrečany]]
*[[Polichno]]
*[[Praha, Slovakia|Praha]]
*[[Prša]]
*[[Radzovce]]
*[[Rapovce]]
*[[Ratka]]
*[[Ružiná]]
*[[Šávoľ]]
*[[Šiatorská Bukovinka]]
*[[Šíd]]
*[[Stará Halič]]
*[[Šurice]]
*[[Točnica]]
*[[Tomášovce, Lučenec District|Tomášovce]]
*[[Trebeľovce]]
*[[Trenč]]
*[[Tuhár]]
*[[Veľká nad Ipľom]]
*[[Veľké Dravce]]
*[[Vidiná]]

== Source ==
*''Lučenec&amp;mdash;ideal place for investment'', published by Lučenec Town Council, Novohradská 1, 98401 Lučenec (Slovakia).

== External links ==
* [http://www.lucenec.sk/ Official site]

{{Banska Bystrica Region}}

{{coord|48|19|48|N|19|39|49|E|source:itwiki_type:adm2nd|display=title}}

{{DEFAULTSORT:Lucenec District}}
[[Category:Districts of Slovakia]]</text>
      <sha1>d5jiqeqle56ulq4k69lql5m3pdu13t1</sha1>
      <model>wikitext</model>
      <format>text/x-wiki</format>
    </revision>
  </page>